{"questionCount":4,"questions":[{"_id":"CBSE Class X\/constructions\/intermediate-1105","level":"intermediate","bank":"B1","funny":false,"type":"4100"},{"_id":"CBSE Class X\/constructions\/intermediate-1106","level":"intermediate","bank":"B2","funny":false,"type":"2210"},{"_id":"CBSE Class X\/constructions\/intermediate-1111","level":"intermediate","bank":"B3","funny":false,"text":"True","type":"2100"},{"_id":"CBSE Class X\/constructions\/intermediate-1108","level":"intermediate","bank":"B4","funny":false,"text":"False","type":"2100"}]}